[
  {
    "ListId": "564319cf1c2042e7984fcd6d",
    "label": "Candidates",
    "categories": [
      {
        "label": "Not Categorised",
        "technologies": [
          {
            "label": "README: CARD TEMPLATE/GUIDELINES",
            "category": "Not Categorised",
            "ring": "Candidates"
          },
          {
            "label": "Subresource Integrity",
            "category": "Not Categorised",
            "ring": "Candidates"
          },
          {
            "label": "CRIU",
            "category": "Not Categorised",
            "ring": "Candidates"
          },
          {
            "label": "AWS SQS",
            "category": "Not Categorised",
            "ring": "Candidates"
          },
          {
            "label": "AWS SNS",
            "category": "Not Categorised",
            "ring": "Candidates"
          },
          {
            "label": "AWS Glacier",
            "category": "Not Categorised",
            "ring": "Candidates"
          },
          {
            "label": "AWS Aurora",
            "category": "Not Categorised",
            "ring": "Candidates"
          }
        ]
      },
      {
        "label": "Platforms",
        "technologies": [
          {
            "label": "React Native",
            "category": "Platforms",
            "ring": "Candidates"
          },
          {
            "label": "AWS Lambda",
            "category": "Platforms",
            "ring": "Candidates"
          }
        ]
      },
      {
        "label": "Techniques",
        "technologies": [
          {
            "label": "Chaos Engineering",
            "category": "Techniques",
            "ring": "Candidates"
          }
        ]
      },
      {
        "label": "Tools",
        "technologies": [
          {
            "label": "Jut.IO",
            "category": "Tools",
            "ring": "Candidates"
          }
        ]
      }
    ]
  },
  {
    "ListId": "564319ef5c3ab1fee0458bd4",
    "label": "Adopt Confidently",
    "categories": [
      {
        "label": "Not Categorised",
        "technologies": [
          {
            "label": "OpenTSDB",
            "category": "Not Categorised",
            "ring": "Adopt Confidently"
          },
          {
            "label": "Maven",
            "category": "Not Categorised",
            "ring": "Adopt Confidently"
          },
          {
            "label": "REST Assured",
            "category": "Not Categorised",
            "ring": "Adopt Confidently"
          },
          {
            "label": "Metrilyx",
            "category": "Not Categorised",
            "ring": "Adopt Confidently"
          },
          {
            "label": "Cucumber",
            "category": "Not Categorised",
            "ring": "Adopt Confidently"
          },
          {
            "label": "Marionette JS",
            "category": "Not Categorised",
            "ring": "Adopt Confidently"
          },
          {
            "label": "Google Guava",
            "category": "Not Categorised",
            "ring": "Adopt Confidently"
          },
          {
            "label": "properties files",
            "category": "Not Categorised",
            "ring": "Adopt Confidently"
          },
          {
            "label": "SOLR",
            "category": "Not Categorised",
            "ring": "Adopt Confidently"
          },
          {
            "label": "WireMock",
            "category": "Not Categorised",
            "ring": "Adopt Confidently"
          },
          {
            "label": "Twig (PHP Template Engine)",
            "category": "Not Categorised",
            "ring": "Adopt Confidently"
          },
          {
            "label": "Symfony Components (PHP)",
            "category": "Not Categorised",
            "ring": "Adopt Confidently"
          },
          {
            "label": "Hazelcast",
            "category": "Not Categorised",
            "ring": "Adopt Confidently"
          },
          {
            "label": "Java 8",
            "category": "Not Categorised",
            "ring": "Adopt Confidently"
          },
          {
            "label": "Tomcat 7",
            "category": "Not Categorised",
            "ring": "Adopt Confidently"
          },
          {
            "label": "Spring 4.x",
            "category": "Not Categorised",
            "ring": "Adopt Confidently"
          },
          {
            "label": "mySQL",
            "category": "Not Categorised",
            "ring": "Adopt Confidently"
          },
          {
            "label": "Oracle (Database)",
            "category": "Not Categorised",
            "ring": "Adopt Confidently"
          }
        ]
      },
      {
        "label": "Tools",
        "technologies": [
          {
            "label": "Composer (Dependency Manager for PHP)",
            "category": "Tools",
            "ring": "Adopt Confidently"
          },
          {
            "label": "Jenkins",
            "category": "Tools",
            "ring": "Adopt Confidently"
          },
          {
            "label": "maven-enforcer",
            "category": "Tools",
            "ring": "Adopt Confidently"
          }
        ]
      },
      {
        "label": "Platforms",
        "technologies": [
          {
            "label": "Angular.js",
            "category": "Platforms",
            "ring": "Adopt Confidently"
          }
        ]
      },
      {
        "label": "Techniques",
        "technologies": [
          {
            "label": "consumer-driven contract testing",
            "category": "Techniques",
            "ring": "Adopt Confidently"
          },
          {
            "label": "focus on mean-time-to-recover",
            "category": "Techniques",
            "ring": "Adopt Confidently"
          },
          {
            "label": "generated infrastructure diagrams",
            "category": "Techniques",
            "ring": "Adopt Confidently"
          },
          {
            "label": "structured logging",
            "category": "Techniques",
            "ring": "Adopt Confidently"
          },
          {
            "label": "domain-driven design",
            "category": "Techniques",
            "ring": "Adopt Confidently"
          },
          {
            "label": "immutability by default",
            "category": "Techniques",
            "ring": "Adopt Confidently"
          },
          {
            "label": "asynchronous messaging over queues",
            "category": "Techniques",
            "ring": "Adopt Confidently"
          },
          {
            "label": "behavior-driven development",
            "category": "Techniques",
            "ring": "Adopt Confidently"
          }
        ]
      }
    ]
  },
  {
    "ListId": "56431a0a1b9ea2159950a2cd",
    "label": "Adopt Cautiously",
    "categories": [
      {
        "label": "Not Categorised",
        "technologies": [
          {
            "label": "NetflixOSS Hystrix",
            "category": "Not Categorised",
            "ring": "Adopt Cautiously"
          },
          {
            "label": "Docker",
            "category": "Not Categorised",
            "ring": "Adopt Cautiously"
          },
          {
            "label": "Spock framework",
            "category": "Not Categorised",
            "ring": "Adopt Cautiously"
          },
          {
            "label": "Dashing.io",
            "category": "Not Categorised",
            "ring": "Adopt Cautiously"
          },
          {
            "label": "PlantUML",
            "category": "Not Categorised",
            "ring": "Adopt Cautiously"
          },
          {
            "label": "Spring Cloud Config",
            "category": "Not Categorised",
            "ring": "Adopt Cautiously"
          },
          {
            "label": "HTTP Strict Transport Security (HSTS)",
            "category": "Not Categorised",
            "ring": "Adopt Cautiously"
          },
          {
            "label": "Swagger",
            "category": "Not Categorised",
            "ring": "Adopt Cautiously"
          },
          {
            "label": "Gradle",
            "category": "Not Categorised",
            "ring": "Adopt Cautiously"
          },
          {
            "label": "ØMQ (ZeroMQ)",
            "category": "Not Categorised",
            "ring": "Adopt Cautiously"
          },
          {
            "label": "Chef configuration management",
            "category": "Not Categorised",
            "ring": "Adopt Cautiously"
          },
          {
            "label": "Redis",
            "category": "Not Categorised",
            "ring": "Adopt Cautiously"
          },
          {
            "label": "Elasticsearch",
            "category": "Not Categorised",
            "ring": "Adopt Cautiously"
          },
          {
            "label": "RabbitMQ",
            "category": "Not Categorised",
            "ring": "Adopt Cautiously"
          },
          {
            "label": "Ruby",
            "category": "Not Categorised",
            "ring": "Adopt Cautiously"
          },
          {
            "label": "Scala",
            "category": "Not Categorised",
            "ring": "Adopt Cautiously"
          },
          {
            "label": "Gitlab/Markdown for documentation",
            "category": "Not Categorised",
            "ring": "Adopt Cautiously"
          },
          {
            "label": "Jetty 9",
            "category": "Not Categorised",
            "ring": "Adopt Cautiously"
          },
          {
            "label": "Tomcat 8",
            "category": "Not Categorised",
            "ring": "Adopt Cautiously"
          },
          {
            "label": "React.js",
            "category": "Not Categorised",
            "ring": "Adopt Cautiously"
          },
          {
            "label": "Play framework (Scala)",
            "category": "Not Categorised",
            "ring": "Adopt Cautiously"
          },
          {
            "label": "ActiveMQ",
            "category": "Not Categorised",
            "ring": "Adopt Cautiously"
          },
          {
            "label": "MongoDB",
            "category": "Not Categorised",
            "ring": "Adopt Cautiously"
          }
        ]
      },
      {
        "label": "Techniques",
        "technologies": [
          {
            "label": "non-blocking APIs",
            "category": "Techniques",
            "ring": "Adopt Cautiously"
          },
          {
            "label": "functional programming paradigms",
            "category": "Techniques",
            "ring": "Adopt Cautiously"
          }
        ]
      },
      {
        "label": "Platforms",
        "technologies": [
          {
            "label": "AWS",
            "category": "Platforms",
            "ring": "Adopt Cautiously"
          },
          {
            "label": "Spring Boot",
            "category": "Platforms",
            "ring": "Adopt Cautiously"
          },
          {
            "label": "Vert.x 3.x",
            "category": "Platforms",
            "ring": "Adopt Cautiously"
          }
        ]
      },
      {
        "label": "Tools",
        "technologies": [
          {
            "label": "Python",
            "category": "Tools",
            "ring": "Adopt Cautiously"
          },
          {
            "label": "JavaScript with Node.js",
            "category": "Tools",
            "ring": "Adopt Cautiously"
          }
        ]
      }
    ]
  },
  {
    "ListId": "56431a307ab6f566f2901517",
    "label": "Assess",
    "categories": [
      {
        "label": "Not Categorised",
        "technologies": [
          {
            "label": "NetflixOSS Eureka",
            "category": "Not Categorised",
            "ring": "Assess"
          },
          {
            "label": "http://projects.lidalia.org.uk/slf4j-test/",
            "category": "Not Categorised",
            "ring": "Assess"
          },
          {
            "label": "RxJava",
            "category": "Not Categorised",
            "ring": "Assess"
          },
          {
            "label": "etcd",
            "category": "Not Categorised",
            "ring": "Assess"
          },
          {
            "label": "HashiCorp Consul",
            "category": "Not Categorised",
            "ring": "Assess"
          },
          {
            "label": "SBT (Scala build tool)",
            "category": "Not Categorised",
            "ring": "Assess"
          },
          {
            "label": "Apache Kafka",
            "category": "Not Categorised",
            "ring": "Assess"
          },
          {
            "label": "Typesafe Config (aka HOCON)",
            "category": "Not Categorised",
            "ring": "Assess"
          },
          {
            "label": "Java Immutables (http://immutables.github.io/immutable.html)",
            "category": "Not Categorised",
            "ring": "Assess"
          },
          {
            "label": "YAML",
            "category": "Not Categorised",
            "ring": "Assess"
          },
          {
            "label": "AWS S3",
            "category": "Not Categorised",
            "ring": "Assess"
          },
          {
            "label": "Apache Storm",
            "category": "Not Categorised",
            "ring": "Assess"
          },
          {
            "label": "Cassandra",
            "category": "Not Categorised",
            "ring": "Assess"
          },
          {
            "label": "ScalaTest",
            "category": "Not Categorised",
            "ring": "Assess"
          },
          {
            "label": "HBase",
            "category": "Not Categorised",
            "ring": "Assess"
          },
          {
            "label": "Memcached",
            "category": "Not Categorised",
            "ring": "Assess"
          },
          {
            "label": "Couchbase",
            "category": "Not Categorised",
            "ring": "Assess"
          },
          {
            "label": "protocol buffers",
            "category": "Not Categorised",
            "ring": "Assess"
          },
          {
            "label": "Avro",
            "category": "Not Categorised",
            "ring": "Assess"
          },
          {
            "label": "Spray.io (Akka-http)",
            "category": "Not Categorised",
            "ring": "Assess"
          },
          {
            "label": "CSP: Content Security Policy",
            "category": "Not Categorised",
            "ring": "Assess"
          },
          {
            "label": "X-Frame-Options",
            "category": "Not Categorised",
            "ring": "Assess"
          },
          {
            "label": "X-XSS-Protection",
            "category": "Not Categorised",
            "ring": "Assess"
          },
          {
            "label": "Amazon Aurora",
            "category": "Not Categorised",
            "ring": "Assess"
          },
          {
            "label": "X-Content-Type-Options: nosniff",
            "category": "Not Categorised",
            "ring": "Assess"
          },
          {
            "label": "Stack PHP",
            "category": "Not Categorised",
            "ring": "Assess"
          },
          {
            "label": "Clojure",
            "category": "Not Categorised",
            "ring": "Assess"
          },
          {
            "label": "NetflixOSS Ribbon",
            "category": "Not Categorised",
            "ring": "Assess"
          },
          {
            "label": "Grafana",
            "category": "Not Categorised",
            "ring": "Assess"
          },
          {
            "label": "Heka",
            "category": "Not Categorised",
            "ring": "Assess"
          }
        ]
      },
      {
        "label": "Languages & Frameworks",
        "technologies": [
          {
            "label": "CoffeeScript",
            "category": "Languages & Frameworks",
            "ring": "Assess"
          },
          {
            "label": ".NET/C#",
            "category": "Languages & Frameworks",
            "ring": "Assess"
          }
        ]
      },
      {
        "label": "Tools",
        "technologies": [
          {
            "label": "HAProxy",
            "category": "Tools",
            "ring": "Assess"
          },
          {
            "label": "ZooKeeper",
            "category": "Tools",
            "ring": "Assess"
          },
          {
            "label": "XHGui/XHProf (PHP)",
            "category": "Tools",
            "ring": "Assess"
          },
          {
            "label": "Satis (Composer Cache for PHP)",
            "category": "Tools",
            "ring": "Assess"
          }
        ]
      },
      {
        "label": "Techniques",
        "technologies": [
          {
            "label": "HTTP/2 & SPDY",
            "category": "Techniques",
            "ring": "Assess"
          },
          {
            "label": "reactive architectures",
            "category": "Techniques",
            "ring": "Assess"
          },
          {
            "label": "WebSocket",
            "category": "Techniques",
            "ring": "Assess"
          },
          {
            "label": "performance-optimized TLS",
            "category": "Techniques",
            "ring": "Assess"
          },
          {
            "label": "IPv6",
            "category": "Techniques",
            "ring": "Assess"
          }
        ]
      },
      {
        "label": "Platforms",
        "technologies": [
          {
            "label": "Akka",
            "category": "Platforms",
            "ring": "Assess"
          }
        ]
      }
    ]
  },
  {
    "ListId": "56431a5af6a6885d2a3fe4e7",
    "label": "Watch",
    "categories": [
      {
        "label": "Not Categorised",
        "technologies": [
          {
            "label": "Spring Framework 5",
            "category": "Not Categorised",
            "ring": "Watch"
          },
          {
            "label": "SaltStack",
            "category": "Not Categorised",
            "ring": "Watch"
          },
          {
            "label": "mountebank (mbtest.org)",
            "category": "Not Categorised",
            "ring": "Watch"
          },
          {
            "label": "Javaslang",
            "category": "Not Categorised",
            "ring": "Watch"
          },
          {
            "label": "Spark Streaming",
            "category": "Not Categorised",
            "ring": "Watch"
          },
          {
            "label": "rkt",
            "category": "Not Categorised",
            "ring": "Watch"
          },
          {
            "label": "Kubernetes",
            "category": "Not Categorised",
            "ring": "Watch"
          },
          {
            "label": "CoreOS fleet",
            "category": "Not Categorised",
            "ring": "Watch"
          },
          {
            "label": "AWS Kinesis",
            "category": "Not Categorised",
            "ring": "Watch"
          },
          {
            "label": "DNSSec",
            "category": "Not Categorised",
            "ring": "Watch"
          },
          {
            "label": "Vaadin",
            "category": "Not Categorised",
            "ring": "Watch"
          },
          {
            "label": "json:api (jsonapi.org)",
            "category": "Not Categorised",
            "ring": "Watch"
          },
          {
            "label": "HAL",
            "category": "Not Categorised",
            "ring": "Watch"
          },
          {
            "label": "Apache Flink",
            "category": "Not Categorised",
            "ring": "Watch"
          },
          {
            "label": "MemSQL",
            "category": "Not Categorised",
            "ring": "Watch"
          }
        ]
      },
      {
        "label": "Platforms",
        "technologies": [
          {
            "label": "AWS ECS",
            "category": "Platforms",
            "ring": "Watch"
          }
        ]
      },
      {
        "label": "Languages & Frameworks",
        "technologies": [
          {
            "label": "Go programming language",
            "category": "Languages & Frameworks",
            "ring": "Watch"
          },
          {
            "label": "Java 9",
            "category": "Languages & Frameworks",
            "ring": "Watch"
          },
          {
            "label": "Rust programming language",
            "category": "Languages & Frameworks",
            "ring": "Watch"
          }
        ]
      },
      {
        "label": "Techniques",
        "technologies": [
          {
            "label": "SDCH HTTP compression",
            "category": "Techniques",
            "ring": "Watch"
          },
          {
            "label": "HATEOAS",
            "category": "Techniques",
            "ring": "Watch"
          }
        ]
      },
      {
        "label": "Tools",
        "technologies": [
          {
            "label": "Spinnaker",
            "category": "Tools",
            "ring": "Watch"
          }
        ]
      }
    ]
  },
  {
    "ListId": "56431a81a9a3375242b4b1fc",
    "label": "Reconsider",
    "categories": [
      {
        "label": "Techniques",
        "technologies": [
          {
            "label": "mock services",
            "category": "Techniques",
            "ring": "Reconsider"
          },
          {
            "label": "doing \"integration testing with Cucumber\"",
            "category": "Techniques",
            "ring": "Reconsider"
          },
          {
            "label": "Scripting CI/CD",
            "category": "Techniques",
            "ring": "Reconsider"
          },
          {
            "label": "long-lived Gitflow branches",
            "category": "Techniques",
            "ring": "Reconsider"
          },
          {
            "label": "separate DevOps teams",
            "category": "Techniques",
            "ring": "Reconsider"
          }
        ]
      },
      {
        "label": "Tools",
        "technologies": [
          {
            "label": "Ant",
            "category": "Tools",
            "ring": "Reconsider"
          },
          {
            "label": "Netflix Asgard",
            "category": "Tools",
            "ring": "Reconsider"
          }
        ]
      },
      {
        "label": "Languages & Frameworks",
        "technologies": [
          {
            "label": "Groovy programming language - For Web Services",
            "category": "Languages & Frameworks",
            "ring": "Reconsider"
          },
          {
            "label": "Java 7 or less",
            "category": "Languages & Frameworks",
            "ring": "Reconsider"
          },
          {
            "label": "Perl",
            "category": "Languages & Frameworks",
            "ring": "Reconsider"
          },
          {
            "label": "C/C++",
            "category": "Languages & Frameworks",
            "ring": "Reconsider"
          },
          {
            "label": "Flash / Flex",
            "category": "Languages & Frameworks",
            "ring": "Reconsider"
          }
        ]
      },
      {
        "label": "Not Categorised",
        "technologies": [
          {
            "label": "Puppet",
            "category": "Not Categorised",
            "ring": "Reconsider"
          },
          {
            "label": "XML",
            "category": "Not Categorised",
            "ring": "Reconsider"
          },
          {
            "label": "Kohana (PHP)",
            "category": "Not Categorised",
            "ring": "Reconsider"
          },
          {
            "label": "Configuration Management Server",
            "category": "Not Categorised",
            "ring": "Reconsider"
          },
          {
            "label": "Cap'n Proto",
            "category": "Not Categorised",
            "ring": "Reconsider"
          },
          {
            "label": "Ruby on Rails",
            "category": "Not Categorised",
            "ring": "Reconsider"
          },
          {
            "label": "Django",
            "category": "Not Categorised",
            "ring": "Reconsider"
          },
          {
            "label": "GWT",
            "category": "Not Categorised",
            "ring": "Reconsider"
          },
          {
            "label": "Ember.js",
            "category": "Not Categorised",
            "ring": "Reconsider"
          },
          {
            "label": "JavaServer Faces",
            "category": "Not Categorised",
            "ring": "Reconsider"
          },
          {
            "label": "enunciate",
            "category": "Not Categorised",
            "ring": "Reconsider"
          },
          {
            "label": "Serf",
            "category": "Not Categorised",
            "ring": "Reconsider"
          }
        ]
      },
      {
        "label": "Platforms",
        "technologies": [
          {
            "label": "Spring 3.x",
            "category": "Platforms",
            "ring": "Reconsider"
          },
          {
            "label": "JBoss",
            "category": "Platforms",
            "ring": "Reconsider"
          }
        ]
      }
    ]
  }
]
